pattern_agentic_messaging/__init__.py
pattern_agentic_messaging/app.py
pattern_agentic_messaging/auth.py
pattern_agentic_messaging/config.py
pattern_agentic_messaging/exceptions.py
pattern_agentic_messaging/messages.py
pattern_agentic_messaging/messaging.py
pattern_agentic_messaging/session.py
pattern_agentic_messaging/types.py
pattern_agentic_messaging/utils.py
pattern_agentic_messaging-1.0.0.dist-info/METADATA
pattern_agentic_messaging-1.0.0.dist-info/WHEEL
pattern_agentic_messaging-1.0.0.dist-info/licenses/LICENSE.md
pattern_agentic_messaging-1.0.0.dist-info/RECORD
