Metadata-Version: 2.4
Name: pattern_agentic_messaging
Version: 1.0.0
Summary: SLIM-powered messaging
Author-email: Amos Joshua <amos@patternagentic.ai>
License-File: LICENSE.md
Classifier: License :: OSI Approved :: MIT License
Classifier: Operating System :: OS Independent
Classifier: Programming Language :: Python :: 3
Requires-Python: >=3.11
Requires-Dist: slim-bindings<0.8.0,>=0.7.0
